panel_indicator/__init__.py
panel_indicator-0.0.1.dev1.dist-info/LICENSE
panel_indicator-0.0.1.dev1.dist-info/METADATA
panel_indicator-0.0.1.dev1.dist-info/WHEEL
panel_indicator-0.0.1.dev1.dist-info/top_level.txt
panel_indicator-0.0.1.dev1.dist-info/RECORD
