Metadata-Version: 2.1
Name: panel-indicator
Version: 0.0.1.dev1
Summary: A library to display any text in ubuntu unity panel
Home-page: https://github.com/ketankr9/panel-indicator.git
Author: Utsav Krishnan
Author-email: ketankr9@gmail.com
License: UNKNOWN
Platform: UNKNOWN
Classifier: Programming Language :: Python :: 3
Classifier: License :: OSI Approved :: MIT License
Classifier: Operating System :: Unix
Requires-Python: >=3.6
Requires-Dist: PyGObject (>=3.34.0)
Requires-Dist: pycairo
